{
  "schema": "streaming_convergence_report.v1",
  "score_mode": "composite_primary",
  "direction": "higher",
  "eval_interval_epochs": 0,
  "patience": 3,
  "min_relative_improvement": 0.01,
  "plateau_met": false,
  "num_validation_checkpoints": 0,
  "recent_relative_improvements": [],
  "history": [
    {
      "epoch": 1,
      "train_loss": 20.174736247575268,
      "validation_score": null,
      "validation_examples": null
    },
    {
      "epoch": 2,
      "train_loss": 13.977948182644973,
      "validation_score": null,
      "validation_examples": null
    },
    {
      "epoch": 3,
      "train_loss": 12.64384455473974,
      "validation_score": null,
      "validation_examples": null
    },
    {
      "epoch": 4,
      "train_loss": 11.975227051894718,
      "validation_score": null,
      "validation_examples": null
    },
    {
      "epoch": 5,
      "train_loss": 11.52819778561167,
      "validation_score": null,
      "validation_examples": null
    },
    {
      "epoch": 6,
      "train_loss": 11.188527271095017,
      "validation_score": null,
      "validation_examples": null
    },
    {
      "epoch": 7,
      "train_loss": 10.88113244031841,
      "validation_score": null,
      "validation_examples": null
    },
    {
      "epoch": 8,
      "train_loss": 10.6375931662119,
      "validation_score": null,
      "validation_examples": null
    }
  ],
  "report_path": "outputs/idm_streaming_d2e_full_state_sequence_stack5_prior_paper_target/convergence_report.json"
}
